README.md
setup.py
satadd/__init__.py
satadd/async_download.py
satadd/authenticator.py
satadd/bandtypes.py
satadd/batchreproject.py
satadd/cli_metadata.py
satadd/config_refresh.py
satadd/ee_rep.py
satadd/exp_report.py
satadd/export.py
satadd/gbdx_fpexport.py
satadd/gbdx_mexport.py
satadd/gbdx_validate.py
satadd/gitcl.py
satadd/idsearch.py
satadd/kml2ee.py
satadd/multipath.py
satadd/multiproc_pydl.py
satadd/satadd.py
satadd/satellogic_auth.py
satadd/satellogic_bandlist.py
satadd/satellogic_imagery.py
satadd/satellogic_metadata.py
satadd/satellogic_metalist.py
satadd/simplesearch.py
satadd.egg-info/PKG-INFO
satadd.egg-info/SOURCES.txt
satadd.egg-info/dependency_links.txt
satadd.egg-info/entry_points.txt
satadd.egg-info/requires.txt
satadd.egg-info/top_level.txt