Metadata-Version: 2.1
Name: satadd
Version: 0.0.4
Summary: Simple CLI for piping Planet, Satellogic, GEE & GBDX Assets
Home-page: https://github.com/samapriya/satadd
Author: Samapriya Roy
Author-email: samapriya.roy@gmail.com
License: Apache 2.0
Platform: UNKNOWN
Classifier: Development Status :: 3 - Alpha
Classifier: Intended Audience :: Developers
Classifier: Intended Audience :: Science/Research
Classifier: Natural Language :: English
Classifier: License :: OSI Approved :: Apache Software License
Classifier: Programming Language :: Python
Classifier: Programming Language :: Python :: 2.7
Classifier: Programming Language :: Python :: 3.6
Classifier: Programming Language :: Python :: 3.7
Classifier: Operating System :: OS Independent
Classifier: Topic :: Scientific/Engineering :: GIS
